healthinsight/__init__.py
healthinsight/Calculations.py
healthinsight-0.0.1.dist-info/METADATA
healthinsight-0.0.1.dist-info/WHEEL
healthinsight-0.0.1.dist-info/RECORD
