Metadata-Version: 2.3
Name: healthinsight
Version: 0.0.1
Summary: A unified package for health indicators and indices e.g. BMI, BAI, etc.
License: MIT
Keywords: health,bmi,bai,body indices,health insights
Author: Olajide Oluwafemi Richard
Author-email: olajidericharhard44@gmail.com
Requires-Python: >=3.8
Classifier: License :: OSI Approved :: MIT License
Classifier: Programming Language :: Python :: 3
Classifier: Programming Language :: Python :: 3.8
Classifier: Programming Language :: Python :: 3.9
Classifier: Programming Language :: Python :: 3.10
Classifier: Programming Language :: Python :: 3.11
Classifier: Programming Language :: Python :: 3.12
Classifier: Programming Language :: Python :: 3.13
Provides-Extra: dev
Requires-Dist: pytest ; extra == "dev"
Requires-Dist: radon ; extra == "dev"
